{"ReturnCode":"API0001","Data":{"Id":2331640,"ShopId":2443,"MoreInfo":{"SalePage_Id":"2331640","SaleProduct_Id":2331401,"SaleProduct_Title":"優寶 3效化毛膏 化毛+卵磷質+鱈魚肝油 100g \u003e可超取 (E632A01)","SaleProductDesc_Content":"\u003cHTML\u003e\u003cheader\u003e\u003cmeta name=\"viewport\" content=\"width=device-width, initial-scale=1, maximum-scale=15.0, user-scalable=yes\"\u003e\u003cstyle\u003eimg, div{max-width: 100%;height: auto;}div[align=\"center\"]\u003ecenter\u003etable,div[align=\"center\"]\u003ecenter\u003etable *{width: 100% !important;} div[align=\"center\"]\u003ecenter\u003etable img{max-width:750px;}div[align=\"center\"]\u003ecenter\u003etable tr td p,div[align=\"center\"]\u003ecenter\u003etable tr td{width:auto!important;}\u003c/style\u003e\u003c/header\u003e\u003cbody\u003e\u003cp\u003e3效化毛膏- 化毛+卵磷質+鱈魚肝油\u003c/p\u003e\u003cp\u003e\u003cbr\u003e\u003c/p\u003e\u003cp\u003e優寶三效化毛膏，特別添加卵磷質、鱈魚肝油及維他命E，\u003c/p\u003e\u003cp\u003e可以補充寵物在排毛過程中，可能流失的營養素、進而維持並促進寵物毛髮及皮膚的健康。\u003c/p\u003e\u003cp\u003e\u003cbr\u003e\u003c/p\u003e\u003cp\u003e成分:白臘油、麥芽糖、卵磷質、鱈魚肝油、焦糖、苯甲酸鈉、維生素E、純水\u003c/p\u003e\u003cp\u003e營養分析(每100公克):熱量 80大卡、蛋白質5公克、脂肪3公克 、飽和脂肪0公克、反式脂肪0公克、碳水化合物0公克、鈉0.2公克\u003c/p\u003e\u003cp\u003e\u003cbr\u003e\u003c/p\u003e\u003cp\u003e用法、用量：\u003c/p\u003e\u003cp\u003e1.可直接餵食或塗少量在貓爪上，方便舔食\u003c/p\u003e\u003cp\u003e2.每日2-3公分的量\u003c/p\u003e\u003cp\u003e\u003cbr\u003e\u003c/p\u003e\u003cp\u003e適用:6月齡以上貓、犬、小動物\u003c/p\u003e\u003cp\u003e\u003cbr\u003e\u003c/p\u003e\u003cp\u003e淨重:100公克\u003c/p\u003e\u003cp\u003e\u003cbr\u003e\u003c/p\u003e\u003cp\u003e產地：澳洲\u003c/p\u003e\u003c/body\u003e\u003c/HTML\u003e"},"MoreInfoVideo":null,"NotKeyPropertyList":[]},"Message":null}