{"ReturnCode":"API0001","Data":{"Id":7524232,"ShopId":2443,"MoreInfo":{"SalePage_Id":"7524232","SaleProduct_Id":7523584,"SaleProduct_Title":"【特價100元，效期2022年10月】日本國產 日本藤澤 貓咪柴魚薄片/鰹魚片 30g 可超取 (D002E31)","SaleProductDesc_Content":"\u003cHTML\u003e\u003cheader\u003e\u003cmeta name=\"viewport\" content=\"width=device-width, initial-scale=1, maximum-scale=15.0, user-scalable=yes\"\u003e\u003cstyle\u003eimg, div{max-width: 100%;height: auto;}div[align=\"center\"]\u003ecenter\u003etable,div[align=\"center\"]\u003ecenter\u003etable *{width: 100% !important;} div[align=\"center\"]\u003ecenter\u003etable img{max-width:750px;}div[align=\"center\"]\u003ecenter\u003etable tr td p,div[align=\"center\"]\u003ecenter\u003etable tr td{width:auto!important;}\u003c/style\u003e\u003c/header\u003e\u003cbody\u003e\u003cp\u003e日本藤澤 貓用柴魚薄片 30g\u003c/p\u003e\u003cp\u003e\u003cbr\u003e\u003c/p\u003e\u003cul\u003e\u003cli\u003e日本國產製作\u003c/li\u003e\u003c/ul\u003e\u003cul\u003e\u003cli\u003e可以撒在主食或是罐罐上當作獎勵\u003c/li\u003e\u003c/ul\u003e\u003cul\u003e\u003cli\u003e使用新鮮日本鰹魚製成，口感鬆軟好吃\u003c/li\u003e\u003c/ul\u003e\u003cp\u003e\u003cbr\u003e\u003c/p\u003e\u003cp\u003e成分：鰹魚片\u003c/p\u003e\u003cp\u003e營養分析：粗蛋白質70.0％以上、粗脂肪3.0％以上、粗纖維0.5％以下、粗灰分5.0％以下、水分20.0％以下，卡路里351kcal / 100g\u003c/p\u003e\u003cp\u003e\u003cbr\u003e\u003c/p\u003e\u003cp\u003e產地：日本\u003c/p\u003e\u003cp\u003e\u003cbr\u003e\u003c/p\u003e\u003cp\u003e餵食方式：開封後直接餵食\u003c/p\u003e\u003cp\u003e每日建議食用量：如包裝上標示\u003c/p\u003e\u003cp\u003e\u003cspan style=\"color: rgb(255, 0, 255); font-weight: bold\"\u003e注意事項：勿存放於嬰幼兒易取處\u003c/span\u003e\u003c/p\u003e\u003cp\u003e\u003cspan style=\"color: rgb(255, 0, 255); background-color: rgb(255, 255, 0); font-weight: bold\"\u003e★★請將本品存放於陰涼處，開封後請冷藏保存並盡速餵食完畢★★\u003c/span\u003e\u003c/p\u003e\u003c/body\u003e\u003c/HTML\u003e"},"MoreInfoVideo":null,"NotKeyPropertyList":[]},"Message":null}